{
  "categories": [
    {
      "id": "js_basics",
      "name": "JavaScript Basics",
      "questions": [
        {
          "id": "q1",
          "question": "What is the correct syntax for referring to an external script called 'script.js'?",
          "options": [
            "A. <script name='script.js'>",
            "B. <script href='script.js'>",
            "C. <script src='script.js'>",
            "D. <script file='script.js'>"
          ],
          "correctAnswer": "C",
          "timeLimit": 10
        },
        {
          "id": "q2",
          "question": "Which company developed JavaScript?",
          "options": ["A. Microsoft", "B. Netscape", "C. Google", "D. Mozilla"],
          "correctAnswer": "B",
          "timeLimit": 10
        },
        {
          "id": "q3",
          "question": "How do you declare a JavaScript variable?",
          "options": [
            "A. var myVariable;",
            "B. let myVariable;",
            "C. const myVariable;",
            "D. All of the above"
          ],
          "correctAnswer": "D",
          "timeLimit": 10
        },
        {
          "id": "q4",
          "question": "Which method can be used to round a number to the nearest integer in JavaScript?",
          "options": [
            "A. Math.round()",
            "B. Math.floor()",
            "C. Math.ceil()",
            "D. Math.random()"
          ],
          "correctAnswer": "A",
          "timeLimit": 10
        },
        {
          "id": "q5",
          "question": "Which of the following is a correct way to create an array in JavaScript?",
          "options": [
            "A. var arr = [];",
            "B. var arr = Array();",
            "C. var arr = new Array();",
            "D. All of the above"
          ],
          "correctAnswer": "D",
          "timeLimit": 10
        }
      ]
    },
    {
      "id": "react_basics",
      "name": "React.js Basics",
      "questions": [
        {
          "id": "q1",
          "question": "What is a React component?",
          "options": [
            "A. A function or class that returns JSX",
            "B. A function that returns HTML",
            "C. A class that extends JavaScript",
            "D. A function that manipulates the DOM"
          ],
          "correctAnswer": "A",
          "timeLimit": 10
        },
        {
          "id": "q2",
          "question": "Which method is used to update the state in a React component?",
          "options": [
            "A. updateState()",
            "B. setState()",
            "C. changeState()",
            "D. modifyState()"
          ],
          "correctAnswer": "B",
          "timeLimit": 10
        },
        {
          "id": "q3",
          "question": "How can you pass data from a parent component to a child component?",
          "options": [
            "A. Using state",
            "B. Using props",
            "C. Using events",
            "D. Using refs"
          ],
          "correctAnswer": "B",
          "timeLimit": 10
        },
        {
          "id": "q4",
          "question": "What hook is used to manage side effects in React?",
          "options": [
            "A. useState",
            "B. useEffect",
            "C. useReducer",
            "D. useContext"
          ],
          "correctAnswer": "B",
          "timeLimit": 10
        },
        {
          "id": "q5",
          "question": "How do you create a React app using the command line?",
          "options": [
            "A. create-react-app myApp",
            "B. npx create-react-app myApp",
            "C. npm install react-app myApp",
            "D. yarn add react-app"
          ],
          "correctAnswer": "B",
          "timeLimit": 10
        }
      ]
    },
    {
      "id": "angular_basics",
      "name": "Angular Basics",
      "questions": [
        {
          "id": "q1",
          "question": "Which of the following is a valid Angular directive?",
          "options": [
            "A. ng-bind",
            "B. ng-model",
            "C. ng-if",
            "D. All of the above"
          ],
          "correctAnswer": "D",
          "timeLimit": 10
        },
        {
          "id": "q2",
          "question": "What is Angular primarily used for?",
          "options": [
            "A. Backend development",
            "B. Mobile app development",
            "C. Frontend web development",
            "D. Database management"
          ],
          "correctAnswer": "C",
          "timeLimit": 10
        },
        {
          "id": "q3",
          "question": "Which of the following is used to define a component in Angular?",
          "options": [
            "A. @Directive",
            "B. @Pipe",
            "C. @Component",
            "D. @Injectable"
          ],
          "correctAnswer": "C",
          "timeLimit": 10
        },
        {
          "id": "q4",
          "question": "Which Angular CLI command is used to generate a new component?",
          "options": [
            "A. ng new component",
            "B. ng add component",
            "C. ng generate component",
            "D. ng make component"
          ],
          "correctAnswer": "C",
          "timeLimit": 10
        },
        {
          "id": "q5",
          "question": "What is the primary programming language used in Angular?",
          "options": ["A. JavaScript", "B. TypeScript", "C. Java", "D. Python"],
          "correctAnswer": "B",
          "timeLimit": 10
        }
      ]
    },
    {
      "id": "flutter_basics",
      "name": "Flutter Basics",
      "questions": [
        {
          "id": "q1",
          "question": "Which programming language is used to write Flutter apps?",
          "options": ["A. Java", "B. Kotlin", "C. Dart", "D. Swift"],
          "correctAnswer": "C",
          "timeLimit": 10
        },
        {
          "id": "q2",
          "question": "What is the primary function of Flutter?",
          "options": [
            "A. Web development",
            "B. Cross-platform mobile development",
            "C. Game development",
            "D. Server-side development"
          ],
          "correctAnswer": "B",
          "timeLimit": 10
        },
        {
          "id": "q3",
          "question": "Which widget in Flutter is used to create a layout?",
          "options": [
            "A. Container",
            "B. Scaffold",
            "C. Column",
            "D. All of the above"
          ],
          "correctAnswer": "D",
          "timeLimit": 10
        },
        {
          "id": "q4",
          "question": "What tool is used to manage Flutter packages?",
          "options": ["A. npm", "B. pub", "C. pip", "D. brew"],
          "correctAnswer": "B",
          "timeLimit": 10
        },
        {
          "id": "q5",
          "question": "Which of the following is a valid state management solution in Flutter?",
          "options": [
            "A. Bloc",
            "B. Provider",
            "C. Redux",
            "D. All of the above"
          ],
          "correctAnswer": "D",
          "timeLimit": 10
        }
      ]
    }
  ]
}
